education_inquiry/__init__.py
education_inquiry/education_inquiry_template.py
education_inquiry_package-0.3.dist-info/METADATA
education_inquiry_package-0.3.dist-info/WHEEL
education_inquiry_package-0.3.dist-info/top_level.txt
education_inquiry_package-0.3.dist-info/RECORD
