Metadata-Version: 2.1
Name: education-inquiry-package
Version: 0.3
Requires-Dist: joblib
Requires-Dist: pandas
Requires-Dist: numpy
Requires-Dist: nltk
Requires-Dist: torch
Requires-Dist: transformers
Requires-Dist: spellchecker
Requires-Dist: gensim
Requires-Dist: scikit-learn
